pyibt/read_ibt.py
pyibt/sweep.py
pyibt-0.0.2.dist-info/LICENSE
pyibt-0.0.2.dist-info/METADATA
pyibt-0.0.2.dist-info/WHEEL
pyibt-0.0.2.dist-info/top_level.txt
pyibt-0.0.2.dist-info/RECORD
