Metadata-Version: 2.1
Name: pyibt
Version: 0.0.2
Summary: Python module for analyzing electrophysiological data
Home-page: https://github.com/pspratt/pyibt
Author: Perry Sprat
Author-email: perrywespratt@gmail.com
License: MIT License
Platform: any
Requires-Dist: matplotlib (>=2.1.0)
Requires-Dist: numpy (>=1.13.3)
